fireviz/__init__.py
fireviz/viz.py
fireviz-0.1.3.dist-info/METADATA
fireviz-0.1.3.dist-info/WHEEL
fireviz-0.1.3.dist-info/top_level.txt
fireviz-0.1.3.dist-info/RECORD
