Metadata-Version: 2.1
Name: fireviz
Version: 0.1.3
Summary: A quick and elegant visualization package for data analysis.
Home-page: https://github.com/AnnNaserNabil/fireviz
Author: Ann Naser Nabil
Author-email: ann.naser@gmail.com
Classifier: Programming Language :: Python :: 3
Classifier: License :: OSI Approved :: MIT License
Classifier: Operating System :: OS Independent
Requires-Python: >=3.6
Requires-Dist: pandas
Requires-Dist: matplotlib
Requires-Dist: seaborn
Requires-Dist: plotly
Requires-Dist: networkx
Requires-Dist: squarify
Requires-Dist: numpy
